gridient/__init__.py
gridient/_version.py
gridient/layout.py
gridient/stacks.py
gridient/styling.py
gridient/tables.py
gridient/values.py
gridient/workbook.py
gridient-0.1.3.dist-info/METADATA
gridient-0.1.3.dist-info/WHEEL
gridient-0.1.3.dist-info/top_level.txt
gridient-0.1.3.dist-info/RECORD
