Metadata-Version: 2.4
Name: gridient
Version: 0.1.3
Summary: A Python library for writing calculations to Excel while preserving formulas.
Home-page: https://github.com/yourusername/gridient
Author: Your Name
Author-email: your.email@example.com
Classifier: Programming Language :: Python :: 3
Classifier: License :: OSI Approved :: MIT License
Classifier: Operating System :: OS Independent
Requires-Python: >=3.7
Requires-Dist: xlsxwriter
Requires-Dist: pandas
Requires-Dist: numpy-financial
Dynamic: author
Dynamic: author-email
Dynamic: classifier
Dynamic: description
Dynamic: description-content-type
Dynamic: home-page
Dynamic: requires-dist
Dynamic: requires-python
Dynamic: summary
